sentinelmesh/__init__.py
sentinelmesh/requirements.txt
sentinelmesh/cli/__init__.py
sentinelmesh/cli/sentinel_cli.py
sentinelmesh/dashboard/__init__.py
sentinelmesh/dashboard/app.py
sentinelmesh/dashboard/blocklist.py
sentinelmesh/dashboard/risk_engine.py
sentinelmesh/example/sample_agents.py
sentinelmesh/monitor/__init__.py
sentinelmesh/monitor/agent_tracker.py
sentinelmesh/monitor/mcp_sniffer.py
sentinelmesh/rules/__init__.py
sentinelmesh/rules/blocklist.yaml
sentinelmesh/rules/rule_engine.py
sentinelmesh/rules/rules.yaml
sentinelmesh/tools/__init__.py
sentinelmesh/tools/replay_log.py
sentinelmesh-1.0.0.dist-info/entry_points.txt
sentinelmesh-1.0.0.dist-info/licenses/LICENSE
sentinelmesh-1.0.0.dist-info/WHEEL
sentinelmesh-1.0.0.dist-info/METADATA
sentinelmesh-1.0.0.dist-info/RECORD
