Metadata-Version: 2.4
Name: sentinelmesh
Version: 1.0.0
Summary: A real-time security and policy mesh for MCP-based AI agent communication
Author-email: Rishit Goel <rishit@example.com>
Requires-Python: >=3.7
License-File: LICENSE
Requires-Dist: streamlit
Requires-Dist: pandas
Requires-Dist: pyyaml
